mapteksdk/__init__.py
mapteksdk/context_menu.py
mapteksdk/errors.py
mapteksdk/geometry.py
mapteksdk/operations.py
mapteksdk/overwrite_modes.py
mapteksdk/progress_indicator.py
mapteksdk/capi/__init__.py
mapteksdk/capi/data_transfer.py
mapteksdk/capi/dataengine.py
mapteksdk/capi/dll_loading.py
mapteksdk/capi/drillholemodel.py
mapteksdk/capi/errors.py
mapteksdk/capi/license.py
mapteksdk/capi/mcp.py
mapteksdk/capi/mdf_dlls.py
mapteksdk/capi/modelling.py
mapteksdk/capi/scan.py
mapteksdk/capi/sdp.py
mapteksdk/capi/selection.py
mapteksdk/capi/system.py
mapteksdk/capi/topology.py
mapteksdk/capi/translation.py
mapteksdk/capi/types.py
mapteksdk/capi/util.py
mapteksdk/capi/viewer.py
mapteksdk/capi/visualisation.py
mapteksdk/capi/vulcan.py
mapteksdk/capi/wrapper_base.py
mapteksdk/capi/internal/__init__.py
mapteksdk/capi/internal/application_dll_directory.py
mapteksdk/capi/internal/errors.py
mapteksdk/common/__init__.py
mapteksdk/common/typing.py
mapteksdk/data/__init__.py
mapteksdk/data/annotations.py
mapteksdk/data/block_model_definition.py
mapteksdk/data/block_utilities.py
mapteksdk/data/blocks.py
mapteksdk/data/cells.py
mapteksdk/data/change_reasons.py
mapteksdk/data/colourmaps.py
mapteksdk/data/containers.py
mapteksdk/data/coordinate_systems.py
mapteksdk/data/edges.py
mapteksdk/data/ellipsoid.py
mapteksdk/data/errors.py
mapteksdk/data/facets.py
mapteksdk/data/filled_polygon.py
mapteksdk/data/geotechnical.py
mapteksdk/data/image_registration.py
mapteksdk/data/image_registration_interface.py
mapteksdk/data/images.py
mapteksdk/data/io.py
mapteksdk/data/objectid.py
mapteksdk/data/points.py
mapteksdk/data/primitive_type.py
mapteksdk/data/ribbons.py
mapteksdk/data/rotation.py
mapteksdk/data/scans.py
mapteksdk/data/selection_file.py
mapteksdk/data/selection_group.py
mapteksdk/data/typing.py
mapteksdk/data/units.py
mapteksdk/data/base/__init__.py
mapteksdk/data/base/appearance.py
mapteksdk/data/base/data_object.py
mapteksdk/data/base/topology.py
mapteksdk-1.9.1.dist-info/METADATA
mapteksdk-1.9.1.dist-info/WHEEL
mapteksdk-1.9.1.dist-info/top_level.txt
mapteksdk-1.9.1.dist-info/RECORD
