Metadata-Version: 2.1
Name: mapteksdk
Version: 1.9.1
Summary: Python SDK for MDF-based Maptek products.
Author-email: Maptek <support@maptek.com.au>
License: Maptek End User Licence Agreement
Project-URL: Homepage, https://www.maptek.com
Project-URL: Documentation, https://help.maptek.com/mapteksdk/
Project-URL: Support, https://www.maptek.com/support/index.html
Classifier: Development Status :: 5 - Production/Stable
Classifier: Operating System :: Microsoft :: Windows
Classifier: License :: Other/Proprietary License
Classifier: Programming Language :: Python :: 3.9
Classifier: Programming Language :: Python :: 3.10
Classifier: Programming Language :: Python :: 3.11
Classifier: Programming Language :: Python :: 3.12
Classifier: Natural Language :: English
Classifier: Topic :: Scientific/Engineering
Classifier: Topic :: Scientific/Engineering :: Visualization
Requires-Python: <3.14,>=3.9
Requires-Dist: numpy<2.3.0,>=1.22.4
Requires-Dist: pandas<2.3.0,>=2.1.0
Requires-Dist: psutil<6.2.0,>=5.8.0
Requires-Dist: pythonnet<3.1.0,>=3.0.0.post1
Requires-Dist: pillow<11.2.0,>=8.0.0
Requires-Dist: pyproj<3.8.0,>=3.5.0
